git_tagup/__init__.py
git_tagup/__main__.py
git_tagup/util.py
git_tagup-0.1.2.dist-info/METADATA
git_tagup-0.1.2.dist-info/WHEEL
git_tagup-0.1.2.dist-info/entry_points.txt
git_tagup-0.1.2.dist-info/top_level.txt
git_tagup-0.1.2.dist-info/RECORD
