Metadata-Version: 2.1
Name: git-tagup
Version: 0.1.2
Summary: Find and tag Git commits based on version numbers in commit messages.
Home-page: https://initialcommit.com/projects/git-tagup
Author: Jacob Stopak
Author-email: jacob@initialcommit.io
License: UNKNOWN
Project-URL: Homepage, https://initialcommit.com/projects/git-tagup
Keywords: git tag git-tagup tagup tag-up version autotag auto-tag commit message
Platform: UNKNOWN
Classifier: Programming Language :: Python :: 3
Classifier: License :: OSI Approved :: MIT License
Classifier: Operating System :: OS Independent
Requires-Python: >=3.6
Requires-Dist: gitpython
